{"type":"PR","pr":{"number":88,"head":"8599be4ae8a5b5d07368297bc6690f28e1ae176c"},"user":"RinGoku","status":"pending_publish","branch":"cms/書籍紹介～読んでよかった技術書たち～","collection":"post","title":"書籍紹介～読んでよかった技術書たち～","description":"私がこれまで読んだ技術書の中で読んでよかった技術書たちをご紹介します。","objects":{"entry":{"path":"content/post/書籍紹介～読んでよかった技術書たち～.md","sha":"3e49ae024e21e5a051700b9e5f223c52b2928c34"},"files":[{"path":"/static/images/uploads/books.png","sha":"bbee3c0afd620777721e5d873f22020640c274bd"}]},"timeStamp":"2019-03-09T08:00:50.893Z"}